[{"id":"1","username":"jikeytang","name":"豪情","blog":"http://jikey.cnblogs.com","github":"http://github.com/jikeytang","website":"http://www.jscss.me","word":"一直在打杂从未被超越","avatar":"https://avatars0.githubusercontent.com/u/539745?v=3&s=400"},{"id":"02","username":"LjxMoon","name":"残阳破月","blog":"http://www.dmoon.top/","github":"http://github.com/LjxMoon/","website":"http://www.dmoon.top/","word":"希望未来可以感谢现在的我","avatar":"http://olxt96812.bkt.clouddn.com/ljxmoon.jpeg"},{"id":"03","username":"achengfu","name":"fugel","blog":"http://fugel.me/","github":"http://github.com/achengfu/","website":"http://fugel.me/","word":"一条咸鱼","avatar":"https://avatars0.githubusercontent.com/u/12210293?v=3&s=460"},{"id":"04","username":"xiaotimo","name":"小题莫","blog":"http://xiaotimode.blog.163.com/","github":"https://github.com/xiaotimo","website":"http://www.zanwu.com","word":"我勤奋！我好学！我为自己代言","avatar":"https://avatars1.githubusercontent.com/u/22878590?v=3&s=400"}]